Metadata-Version: 1.0
Name: actuwiser-distributions
Version: 0.1
Summary: Gaussian and Binomial Distributions
Home-page: UNKNOWN
Author: Victor Mombeyarara
Author-email: vmombeyarara@gmail.com
License: UNKNOWN
Platform: UNKNOWN
